{"type":"FeatureCollection","features":[{"type":"Feature","properties":{"id":9931530711,"category":"shop","label":"deli"},"geometry":{"type":"Point","coordinates":[105.84785842613474,21.0192867702412]}},{"type":"Feature","properties":{"id":11212195516,"category":"shop","label":"deli"},"geometry":{"type":"Point","coordinates":[105.83434613569736,21.008475538828378]}},{"type":"Feature","properties":{"id":11295820777,"category":"shop","label":"deli"},"geometry":{"type":"Point","coordinates":[105.83201491985085,21.016654521941632]}},{"type":"Feature","properties":{"id":11491290543,"category":"shop","label":"deli"},"geometry":{"type":"Point","coordinates":[105.85024628751454,21.014459257657624]}},{"type":"Feature","properties":{"id":11782452950,"category":"shop","label":"deli"},"geometry":{"type":"Point","coordinates":[105.851395746517,21.015239544918316]}},{"type":"Feature","properties":{"id":904729856,"category":"shop","label":"deli"},"geometry":{"type":"Point","coordinates":[105.84830608353954,21.011668124907004]}},{"type":"Feature","properties":{"id":1329845939,"category":"shop","label":"deli"},"geometry":{"type":"Point","coordinates":[105.7542118026542,21.00580472154407]}},{"type":"Feature","properties":{"id":1331638464,"category":"shop","label":"deli"},"geometry":{"type":"Point","coordinates":[105.86862755539973,20.993378413298906]}}]}