{"type":"FeatureCollection","features":[{"type":"Feature","properties":{"id":4555239812,"category":"shop","label":"pastry"},"geometry":{"type":"Point","coordinates":[38.87695648946952,9.028603429488399]}},{"type":"Feature","properties":{"id":4967654934,"category":"shop","label":"pastry"},"geometry":{"type":"Point","coordinates":[38.81538595989597,9.019438689254217]}},{"type":"Feature","properties":{"id":4968426954,"category":"shop","label":"pastry"},"geometry":{"type":"Point","coordinates":[38.838077403972825,9.021177612362328]}},{"type":"Feature","properties":{"id":6723488310,"category":"shop","label":"pastry"},"geometry":{"type":"Point","coordinates":[38.722221681779935,8.948925416330919]}},{"type":"Feature","properties":{"id":6736192720,"category":"shop","label":"pastry"},"geometry":{"type":"Point","coordinates":[38.68431277679009,9.004355841636501]}},{"type":"Feature","properties":{"id":6742385088,"category":"shop","label":"pastry"},"geometry":{"type":"Point","coordinates":[38.747392476040964,9.022543903212162]}},{"type":"Feature","properties":{"id":6814279384,"category":"shop","label":"pastry"},"geometry":{"type":"Point","coordinates":[38.72029030391908,9.063139895808938]}},{"type":"Feature","properties":{"id":6814283318,"category":"shop","label":"pastry"},"geometry":{"type":"Point","coordinates":[38.713930231707515,8.955536340600336]}},{"type":"Feature","properties":{"id":6837208439,"category":"shop","label":"pastry"},"geometry":{"type":"Point","coordinates":[38.868817752995405,9.065410864968294]}},{"type":"Feature","properties":{"id":9137849087,"category":"shop","label":"pastry"},"geometry":{"type":"Point","coordinates":[38.78066607416475,9.004710739400851]}}]}