{"type":"FeatureCollection","features":[{"type":"Feature","properties":{"id":104770283,"category":"amenity","label":"food_court"},"geometry":{"type":"Point","coordinates":[105.8480767027725,21.039096174269137]}},{"type":"Feature","properties":{"id":1708540209,"category":"amenity","label":"food_court"},"geometry":{"type":"Point","coordinates":[105.85475118533351,21.002905154927785]}},{"type":"Feature","properties":{"id":3316120061,"category":"amenity","label":"food_court"},"geometry":{"type":"Point","coordinates":[105.81617752703343,21.022930372691604]}},{"type":"Feature","properties":{"id":5315672621,"category":"amenity","label":"food_court"},"geometry":{"type":"Point","coordinates":[105.81347359802822,21.074582673551845]}},{"type":"Feature","properties":{"id":5350734821,"category":"amenity","label":"food_court"},"geometry":{"type":"Point","coordinates":[105.81893535495567,21.03530642381286]}},{"type":"Feature","properties":{"id":6035928576,"category":"amenity","label":"food_court"},"geometry":{"type":"Point","coordinates":[105.86208143805193,21.02505181486718]}},{"type":"Feature","properties":{"id":6957667188,"category":"amenity","label":"food_court"},"geometry":{"type":"Point","coordinates":[105.84806771961966,21.032321508243424]}},{"type":"Feature","properties":{"id":7055939380,"category":"amenity","label":"food_court"},"geometry":{"type":"Point","coordinates":[105.83362280985104,20.985267655980326]}},{"type":"Feature","properties":{"id":7178803503,"category":"amenity","label":"food_court"},"geometry":{"type":"Point","coordinates":[105.87371462098129,21.112105483338574]}},{"type":"Feature","properties":{"id":7192525585,"category":"amenity","label":"food_court"},"geometry":{"type":"Point","coordinates":[105.84649566787246,21.032304738885916]}},{"type":"Feature","properties":{"id":892577273,"category":"amenity","label":"food_court"},"geometry":{"type":"Point","coordinates":[105.81624939225615,21.002871609594344]}},{"type":"Feature","properties":{"id":1115212902,"category":"amenity","label":"food_court"},"geometry":{"type":"Point","coordinates":[105.7787087965328,21.06127098860031]}},{"type":"Feature","properties":{"id":1115220861,"category":"amenity","label":"food_court"},"geometry":{"type":"Point","coordinates":[105.77869981337996,21.061882949863097]}},{"type":"Feature","properties":{"id":1115220865,"category":"amenity","label":"food_court"},"geometry":{"type":"Point","coordinates":[105.7780979421396,21.06181588573793]}},{"type":"Feature","properties":{"id":1115533828,"category":"amenity","label":"food_court"},"geometry":{"type":"Point","coordinates":[105.77893337535384,21.06070094022816]}},{"type":"Feature","properties":{"id":1115537725,"category":"amenity","label":"food_court"},"geometry":{"type":"Point","coordinates":[105.77954422974703,21.060449447604952]}},{"type":"Feature","properties":{"id":1115540595,"category":"amenity","label":"food_court"},"geometry":{"type":"Point","coordinates":[105.7789693079652,21.06106141224678]}},{"type":"Feature","properties":{"id":1115657576,"category":"amenity","label":"food_court"},"geometry":{"type":"Point","coordinates":[105.77964304442828,21.06250329158782]}},{"type":"Feature","properties":{"id":1115657581,"category":"amenity","label":"food_court"},"geometry":{"type":"Point","coordinates":[105.77930168462032,21.062008695016313]}},{"type":"Feature","properties":{"id":1247565027,"category":"amenity","label":"food_court"},"geometry":{"type":"Point","coordinates":[105.78234697343349,21.040890403023827]}},{"type":"Feature","properties":{"id":1350647805,"category":"amenity","label":"food_court"},"geometry":{"type":"Point","coordinates":[105.80080735252214,21.01733733498417]}}]}