{"type":"FeatureCollection","features":[{"type":"Feature","properties":{"id":4748316721,"category":"amenity","label":"drinking_water"},"geometry":{"type":"Point","coordinates":[105.80899998791332,20.99855258493614]}},{"type":"Feature","properties":{"id":4758991221,"category":"amenity","label":"drinking_water"},"geometry":{"type":"Point","coordinates":[105.86503689533669,21.00512751647087]}},{"type":"Feature","properties":{"id":5942473585,"category":"amenity","label":"drinking_water"},"geometry":{"type":"Point","coordinates":[105.84778025872875,21.02489249812383]}},{"type":"Feature","properties":{"id":6292723885,"category":"amenity","label":"drinking_water"},"geometry":{"type":"Point","coordinates":[105.85025062576008,21.026376652769088]}},{"type":"Feature","properties":{"id":6698948887,"category":"amenity","label":"drinking_water"},"geometry":{"type":"Point","coordinates":[105.77823268943222,21.06567202382826]}},{"type":"Feature","properties":{"id":9931507054,"category":"amenity","label":"drinking_water"},"geometry":{"type":"Point","coordinates":[105.85344862817155,21.026099947091534]}},{"type":"Feature","properties":{"id":9931530710,"category":"amenity","label":"drinking_water"},"geometry":{"type":"Point","coordinates":[105.85478711794488,21.027584089714345]}},{"type":"Feature","properties":{"id":9931540123,"category":"amenity","label":"drinking_water"},"geometry":{"type":"Point","coordinates":[105.80128345962272,21.21536359274046]}},{"type":"Feature","properties":{"id":10114776470,"category":"amenity","label":"drinking_water"},"geometry":{"type":"Point","coordinates":[105.84452835740024,21.00386958003961]}},{"type":"Feature","properties":{"id":10660753505,"category":"amenity","label":"drinking_water"},"geometry":{"type":"Point","coordinates":[105.85382592059088,21.027349311074378]}},{"type":"Feature","properties":{"id":11191573737,"category":"amenity","label":"drinking_water"},"geometry":{"type":"Point","coordinates":[105.85370913960394,21.029814468348597]}},{"type":"Feature","properties":{"id":11676700469,"category":"amenity","label":"drinking_water"},"geometry":{"type":"Point","coordinates":[105.83404501803457,21.036748552606184]}},{"type":"Feature","properties":{"id":11834019569,"category":"amenity","label":"drinking_water"},"geometry":{"type":"Point","coordinates":[105.85141843562943,21.02804526096617]}},{"type":"Feature","properties":{"id":11865316771,"category":"amenity","label":"drinking_water"},"geometry":{"type":"Point","coordinates":[105.84664838147076,21.031273419772514]}},{"type":"Feature","properties":{"id":11893374272,"category":"amenity","label":"drinking_water"},"geometry":{"type":"Point","coordinates":[105.8519574247999,21.026150257252933]}},{"type":"Feature","properties":{"id":12086821054,"category":"amenity","label":"drinking_water"},"geometry":{"type":"Point","coordinates":[105.83230228638338,21.03464404602603]}},{"type":"Feature","properties":{"id":12129133501,"category":"amenity","label":"drinking_water"},"geometry":{"type":"Point","coordinates":[105.854724235875,21.027265461470474]}},{"type":"Feature","properties":{"id":12278326273,"category":"amenity","label":"drinking_water"},"geometry":{"type":"Point","coordinates":[105.85389778581361,21.031139263916064]}},{"type":"Feature","properties":{"id":12538794304,"category":"amenity","label":"drinking_water"},"geometry":{"type":"Point","coordinates":[105.7899826533485,21.21913199575228]}},{"type":"Feature","properties":{"id":12540668301,"category":"amenity","label":"drinking_water"},"geometry":{"type":"Point","coordinates":[105.78872501195073,21.21947533435488]}},{"type":"Feature","properties":{"id":12540668506,"category":"amenity","label":"drinking_water"},"geometry":{"type":"Point","coordinates":[105.79378252700033,21.218043355876876]}},{"type":"Feature","properties":{"id":12540668510,"category":"amenity","label":"drinking_water"},"geometry":{"type":"Point","coordinates":[105.79515694938503,21.217649768714615]}},{"type":"Feature","properties":{"id":12540668704,"category":"amenity","label":"drinking_water"},"geometry":{"type":"Point","coordinates":[105.79122232844058,21.218746785637517]}},{"type":"Feature","properties":{"id":12690411001,"category":"amenity","label":"drinking_water"},"geometry":{"type":"Point","coordinates":[105.84621719013438,21.017379262584004]}},{"type":"Feature","properties":{"id":13005736901,"category":"amenity","label":"drinking_water"},"geometry":{"type":"Point","coordinates":[105.84724126955828,21.018016560650064]}}]}